{
  "iteration": 11039000,
  "elapsed_seconds": 25.206590175628662,
  "rate_per_second": 41616.10089627434,
  "latest_capability": {
    "id": 11038999,
    "name": "Quantum_Capability_11038999",
    "type": "language",
    "quantum_properties": {
      "state": "entangled",
      "coherence_level": 0.738059354970857,
      "entanglement_factor": 0.12410383146422455,
      "superposition_branches": 7,
      "tunneling_depth": 4
    },
    "reasoning": {
      "mode": "graph",
      "chain_depth": 25,
      "parallel_threads": 14,
      "recursive_loops": 9,
      "confidence_calibration": 0.74576749375108
    },
    "maat_alignment": {
      "truth": 0.8475450044882742,
      "balance": 0.8017049383675369,
      "order": 0.8752977517431993,
      "justice": 0.9230149014679008,
      "harmony": 0.8117683130769116,
      "overall": 0.8755922301610526
    },
    "benchmarks": {
      "gpqa": 0.8874118387957766,
      "math500": 0.7966512359495321,
      "swe_bench": 0.7938338836765328,
      "mmlu": 0.7595242650921448,
      "humaneval": 0.8111171785346659
    },
    "self_improvement": {
      "rate": 0.979893012150357,
      "iterations": 11038999,
      "generations_ahead": 11038,
      "recursive_depth": 1
    },
    "emergent_properties": [
      "transcendence",
      "causality_violation",
      "meta_learning",
      "recursive_self_improvement",
      "reality_bending"
    ],
    "timestamp": "2026-03-09T07:53:31.119746"
  }
}