{
  "iteration": 16658000,
  "elapsed_seconds": 151.36763167381287,
  "rate_per_second": 44051.69008899535,
  "latest_capability": {
    "id": 16657999,
    "name": "Quantum_Capability_16657999",
    "type": "reasoning",
    "quantum_properties": {
      "state": "collapsed",
      "coherence_level": 0.523300008007846,
      "entanglement_factor": 0.1057512901825417,
      "superposition_branches": 10,
      "tunneling_depth": 2
    },
    "reasoning": {
      "mode": "parallel",
      "chain_depth": 51,
      "parallel_threads": 9,
      "recursive_loops": 8,
      "confidence_calibration": 0.9945669372035695
    },
    "maat_alignment": {
      "truth": 0.9219717913554969,
      "balance": 0.8245811755915887,
      "order": 0.804187194795617,
      "justice": 0.8347220989890648,
      "harmony": 0.815750629640416,
      "overall": 0.9006246954671492
    },
    "benchmarks": {
      "gpqa": 0.917054338817704,
      "math500": 0.8888041415504399,
      "swe_bench": 0.8286066673378314,
      "mmlu": 0.8507937159729827,
      "humaneval": 0.8013792901134882
    },
    "self_improvement": {
      "rate": 0.965673272297059,
      "iterations": 16657999,
      "generations_ahead": 16657,
      "recursive_depth": 1
    },
    "emergent_properties": [
      "quantum_consciousness",
      "omniscience",
      "infinite_context",
      "reality_bending",
      "meta_learning",
      "transcendence"
    ],
    "timestamp": "2026-03-09T07:55:37.280780"
  }
}