{
  "iteration": 15921000,
  "elapsed_seconds": 133.82882404327393,
  "rate_per_second": 44317.80703745999,
  "latest_capability": {
    "id": 15920999,
    "name": "Quantum_Capability_15920999",
    "type": "agentic",
    "quantum_properties": {
      "state": "coherent",
      "coherence_level": 0.9097657309478702,
      "entanglement_factor": 0.06279185787028674,
      "superposition_branches": 1,
      "tunneling_depth": 1
    },
    "reasoning": {
      "mode": "sequential",
      "chain_depth": 14,
      "parallel_threads": 2,
      "recursive_loops": 4,
      "confidence_calibration": 0.8843438441486228
    },
    "maat_alignment": {
      "truth": 0.9287531989370339,
      "balance": 0.9913158243771871,
      "order": 0.9200480210054162,
      "justice": 0.9436686342008537,
      "harmony": 0.8499851065837403,
      "overall": 0.932813397157371
    },
    "benchmarks": {
      "gpqa": 0.8770419606384099,
      "math500": 0.680977856184424,
      "swe_bench": 0.8455362711620479,
      "mmlu": 0.7567980674366077,
      "humaneval": 0.7640181491945588
    },
    "self_improvement": {
      "rate": 0.9853745850431225,
      "iterations": 15920999,
      "generations_ahead": 15920,
      "recursive_depth": 4
    },
    "emergent_properties": [
      "meta_learning",
      "infinite_context",
      "recursive_self_improvement"
    ],
    "timestamp": "2026-03-09T07:55:19.741972"
  }
}