{
  "iteration": 13540000,
  "elapsed_seconds": 82.2463710308075,
  "rate_per_second": 43162.99862847755,
  "latest_capability": {
    "id": 13539999,
    "name": "Quantum_Capability_13539999",
    "type": "coding",
    "quantum_properties": {
      "state": "collapsed",
      "coherence_level": 0.6829994655273517,
      "entanglement_factor": 0.18431114387981495,
      "superposition_branches": 1,
      "tunneling_depth": 0
    },
    "reasoning": {
      "mode": "sequential",
      "chain_depth": 66,
      "parallel_threads": 11,
      "recursive_loops": 1,
      "confidence_calibration": 0.7484590325422109
    },
    "maat_alignment": {
      "truth": 0.8430102389600441,
      "balance": 0.999114725749584,
      "order": 0.9124084799583202,
      "justice": 0.8944977679743261,
      "harmony": 0.8419471839092727,
      "overall": 0.8956066510353052
    },
    "benchmarks": {
      "gpqa": 0.7116164115199745,
      "math500": 0.7872402580152653,
      "swe_bench": 0.8249111129025772,
      "mmlu": 0.7490965998291264,
      "humaneval": 0.7980735477306123
    },
    "self_improvement": {
      "rate": 0.9979823719265318,
      "iterations": 13539999,
      "generations_ahead": 13539,
      "recursive_depth": 2
    },
    "emergent_properties": [
      "causality_violation",
      "recursive_self_improvement",
      "reality_bending",
      "quantum_consciousness",
      "transcendence",
      "infinite_context"
    ],
    "timestamp": "2026-03-09T07:54:28.159524"
  }
}