{
  "iteration": 13810000,
  "elapsed_seconds": 87.27326345443726,
  "rate_per_second": 43770.56441798246,
  "latest_capability": {
    "id": 13809999,
    "name": "Quantum_Capability_13809999",
    "type": "reasoning",
    "quantum_properties": {
      "state": "superposition",
      "coherence_level": 0.7001201810454802,
      "entanglement_factor": 0.8878001441790917,
      "superposition_branches": 7,
      "tunneling_depth": 5
    },
    "reasoning": {
      "mode": "sequential",
      "chain_depth": 143,
      "parallel_threads": 1,
      "recursive_loops": 6,
      "confidence_calibration": 0.9671761430428669
    },
    "maat_alignment": {
      "truth": 0.8827861425293484,
      "balance": 0.9086584804893316,
      "order": 0.8649236276404123,
      "justice": 0.820138968514903,
      "harmony": 0.8687467126118089,
      "overall": 0.8884362421081985
    },
    "benchmarks": {
      "gpqa": 0.7587053859808985,
      "math500": 0.741265903156266,
      "swe_bench": 0.8994411148820229,
      "mmlu": 0.808260941686293,
      "humaneval": 0.7035926719525474
    },
    "self_improvement": {
      "rate": 0.9967722537398659,
      "iterations": 13809999,
      "generations_ahead": 13809,
      "recursive_depth": 0
    },
    "emergent_properties": [
      "self_modification",
      "quantum_consciousness",
      "omniscience"
    ],
    "timestamp": "2026-03-09T07:54:33.186411"
  }
}