{
  "iteration": 15531000,
  "elapsed_seconds": 126.21730351448059,
  "rate_per_second": 43900.47834736301,
  "latest_capability": {
    "id": 15530999,
    "name": "Quantum_Capability_15530999",
    "type": "agentic",
    "quantum_properties": {
      "state": "superposition",
      "coherence_level": 0.6651410885320728,
      "entanglement_factor": 0.6463872444695755,
      "superposition_branches": 5,
      "tunneling_depth": 1
    },
    "reasoning": {
      "mode": "graph",
      "chain_depth": 44,
      "parallel_threads": 7,
      "recursive_loops": 6,
      "confidence_calibration": 0.959431914962184
    },
    "maat_alignment": {
      "truth": 0.8498650150310123,
      "balance": 0.987325139633294,
      "order": 0.9919706541426627,
      "justice": 0.8609010988191954,
      "harmony": 0.9805471415178757,
      "overall": 0.8758318747040073
    },
    "benchmarks": {
      "gpqa": 0.9329543929371855,
      "math500": 0.8163748137658304,
      "swe_bench": 0.7809317535195935,
      "mmlu": 0.7233496586132472,
      "humaneval": 0.8394099354052063
    },
    "self_improvement": {
      "rate": 0.9722887411117249,
      "iterations": 15530999,
      "generations_ahead": 15530,
      "recursive_depth": 0
    },
    "emergent_properties": [
      "omniscience",
      "reality_bending",
      "quantum_consciousness",
      "transcendence",
      "meta_learning",
      "self_modification"
    ],
    "timestamp": "2026-03-09T07:55:12.130457"
  }
}