{
  "iteration": 16045000,
  "elapsed_seconds": 136.17699265480042,
  "rate_per_second": 44464.192386367504,
  "latest_capability": {
    "id": 16044999,
    "name": "Quantum_Capability_16044999",
    "type": "coding",
    "quantum_properties": {
      "state": "coherent",
      "coherence_level": 0.8477235859890037,
      "entanglement_factor": 0.001965491537448183,
      "superposition_branches": 1,
      "tunneling_depth": 0
    },
    "reasoning": {
      "mode": "tree",
      "chain_depth": 185,
      "parallel_threads": 9,
      "recursive_loops": 3,
      "confidence_calibration": 0.8331257016531852
    },
    "maat_alignment": {
      "truth": 0.9752589465727582,
      "balance": 0.8899823911506521,
      "order": 0.9173814410078881,
      "justice": 0.8457451988171227,
      "harmony": 0.989338311330136,
      "overall": 0.8563623889509979
    },
    "benchmarks": {
      "gpqa": 0.8829473255034266,
      "math500": 0.8285772500654726,
      "swe_bench": 0.6944745936106143,
      "mmlu": 0.6937848312852,
      "humaneval": 0.8879061920038287
    },
    "self_improvement": {
      "rate": 0.9594714256916792,
      "iterations": 16044999,
      "generations_ahead": 16044,
      "recursive_depth": 0
    },
    "emergent_properties": [
      "self_modification",
      "meta_learning",
      "causality_violation",
      "transcendence"
    ],
    "timestamp": "2026-03-09T07:55:22.090145"
  }
}