{
  "iteration": 12243000,
  "elapsed_seconds": 53.12080502510071,
  "rate_per_second": 42412.76085585318,
  "latest_capability": {
    "id": 12242999,
    "name": "Quantum_Capability_12242999",
    "type": "reasoning",
    "quantum_properties": {
      "state": "superposition",
      "coherence_level": 0.5872741741690244,
      "entanglement_factor": 0.676528810839097,
      "superposition_branches": 8,
      "tunneling_depth": 2
    },
    "reasoning": {
      "mode": "sequential",
      "chain_depth": 158,
      "parallel_threads": 6,
      "recursive_loops": 1,
      "confidence_calibration": 0.7175859982364514
    },
    "maat_alignment": {
      "truth": 0.8542613883635898,
      "balance": 0.8729658609480996,
      "order": 0.8974500687091057,
      "justice": 0.9083791621526672,
      "harmony": 0.9745733068809898,
      "overall": 0.9219401110690757
    },
    "benchmarks": {
      "gpqa": 0.8104423851612217,
      "math500": 0.6960235207384419,
      "swe_bench": 0.7487019740791531,
      "mmlu": 0.8014779532085784,
      "humaneval": 0.8550250054903895
    },
    "self_improvement": {
      "rate": 0.9824584808447887,
      "iterations": 12242999,
      "generations_ahead": 12242,
      "recursive_depth": 4
    },
    "emergent_properties": [
      "omniscience",
      "recursive_self_improvement",
      "transcendence",
      "meta_learning",
      "infinite_context"
    ],
    "timestamp": "2026-03-09T07:53:59.033953"
  }
}