{
  "iteration": 12466000,
  "elapsed_seconds": 57.482415437698364,
  "rate_per_second": 43074.04240316908,
  "latest_capability": {
    "id": 12465999,
    "name": "Quantum_Capability_12465999",
    "type": "coding",
    "quantum_properties": {
      "state": "entangled",
      "coherence_level": 0.5174676360625712,
      "entanglement_factor": 0.44999126191963956,
      "superposition_branches": 8,
      "tunneling_depth": 3
    },
    "reasoning": {
      "mode": "tree",
      "chain_depth": 112,
      "parallel_threads": 8,
      "recursive_loops": 8,
      "confidence_calibration": 0.8306905955744427
    },
    "maat_alignment": {
      "truth": 0.8051868622878656,
      "balance": 0.840405759133231,
      "order": 0.9036311718395622,
      "justice": 0.9987843976360401,
      "harmony": 0.9254439885885665,
      "overall": 0.8621235555880506
    },
    "benchmarks": {
      "gpqa": 0.7185164321664763,
      "math500": 0.8246586615835783,
      "swe_bench": 0.8422091786200132,
      "mmlu": 0.8569176540601869,
      "humaneval": 0.7112738811204743
    },
    "self_improvement": {
      "rate": 0.976242076208944,
      "iterations": 12465999,
      "generations_ahead": 12465,
      "recursive_depth": 0
    },
    "emergent_properties": [
      "quantum_consciousness",
      "recursive_self_improvement",
      "infinite_context",
      "meta_learning",
      "causality_violation"
    ],
    "timestamp": "2026-03-09T07:54:03.395564"
  }
}