{
  "iteration": 15999000,
  "elapsed_seconds": 135.2267735004425,
  "rate_per_second": 44436.466569841934,
  "latest_capability": {
    "id": 15998999,
    "name": "Quantum_Capability_15998999",
    "type": "coding",
    "quantum_properties": {
      "state": "collapsed",
      "coherence_level": 0.7857923401330287,
      "entanglement_factor": 0.1563222787837426,
      "superposition_branches": 7,
      "tunneling_depth": 1
    },
    "reasoning": {
      "mode": "tree",
      "chain_depth": 82,
      "parallel_threads": 16,
      "recursive_loops": 8,
      "confidence_calibration": 0.9828044349767576
    },
    "maat_alignment": {
      "truth": 0.8812361331334998,
      "balance": 0.8804329411985296,
      "order": 0.9437440632752483,
      "justice": 0.9478925706171425,
      "harmony": 0.8579674856827734,
      "overall": 0.9324465888510538
    },
    "benchmarks": {
      "gpqa": 0.8771848113524641,
      "math500": 0.7268922026538726,
      "swe_bench": 0.767936667203203,
      "mmlu": 0.7555325123303313,
      "humaneval": 0.88955364486471
    },
    "self_improvement": {
      "rate": 0.9614803808447715,
      "iterations": 15998999,
      "generations_ahead": 15998,
      "recursive_depth": 0
    },
    "emergent_properties": [
      "omniscience",
      "reality_bending",
      "self_modification",
      "infinite_context"
    ],
    "timestamp": "2026-03-09T07:55:21.139921"
  }
}