{
  "iteration": 17419000,
  "elapsed_seconds": 165.89695692062378,
  "rate_per_second": 44780.80935236522,
  "latest_capability": {
    "id": 17418999,
    "name": "Quantum_Capability_17418999",
    "type": "math",
    "quantum_properties": {
      "state": "coherent",
      "coherence_level": 0.9901581454815915,
      "entanglement_factor": 0.3682201377112416,
      "superposition_branches": 3,
      "tunneling_depth": 5
    },
    "reasoning": {
      "mode": "sequential",
      "chain_depth": 114,
      "parallel_threads": 8,
      "recursive_loops": 1,
      "confidence_calibration": 0.729003292376815
    },
    "maat_alignment": {
      "truth": 0.9863969802281469,
      "balance": 0.8934919293974286,
      "order": 0.8882139337021506,
      "justice": 0.8795177645222638,
      "harmony": 0.978747550741194,
      "overall": 0.8608506471754473
    },
    "benchmarks": {
      "gpqa": 0.9183369290154099,
      "math500": 0.8943084413238906,
      "swe_bench": 0.786180280801782,
      "mmlu": 0.7551076939520335,
      "humaneval": 0.8848700175885995
    },
    "self_improvement": {
      "rate": 0.9677605166079866,
      "iterations": 17418999,
      "generations_ahead": 17418,
      "recursive_depth": 0
    },
    "emergent_properties": [
      "reality_bending",
      "transcendence",
      "recursive_self_improvement",
      "infinite_context",
      "omniscience",
      "quantum_consciousness"
    ],
    "timestamp": "2026-03-09T07:55:51.810106"
  }
}