{
  "iteration": 11908000,
  "elapsed_seconds": 45.5242121219635,
  "rate_per_second": 42131.42656618644,
  "latest_capability": {
    "id": 11907999,
    "name": "Quantum_Capability_11907999",
    "type": "coding",
    "quantum_properties": {
      "state": "superposition",
      "coherence_level": 0.8963954807227796,
      "entanglement_factor": 0.5757483536379501,
      "superposition_branches": 7,
      "tunneling_depth": 0
    },
    "reasoning": {
      "mode": "tree",
      "chain_depth": 99,
      "parallel_threads": 12,
      "recursive_loops": 5,
      "confidence_calibration": 0.9873893737666103
    },
    "maat_alignment": {
      "truth": 0.9123823876430347,
      "balance": 0.9004434911289545,
      "order": 0.9368467708116613,
      "justice": 0.8955143402094284,
      "harmony": 0.9268332729419774,
      "overall": 0.9677112578432552
    },
    "benchmarks": {
      "gpqa": 0.9481094758806863,
      "math500": 0.7051514073112176,
      "swe_bench": 0.814404830404914,
      "mmlu": 0.881226912965885,
      "humaneval": 0.9461648917002807
    },
    "self_improvement": {
      "rate": 0.970998715908675,
      "iterations": 11907999,
      "generations_ahead": 11907,
      "recursive_depth": 1
    },
    "emergent_properties": [
      "self_modification",
      "infinite_context",
      "meta_learning"
    ],
    "timestamp": "2026-03-09T07:53:51.437360"
  }
}