{
  "iteration": 12175000,
  "elapsed_seconds": 51.82379388809204,
  "rate_per_second": 42162.100380344105,
  "latest_capability": {
    "id": 12174999,
    "name": "Quantum_Capability_12174999",
    "type": "agentic",
    "quantum_properties": {
      "state": "collapsed",
      "coherence_level": 0.9853834422697769,
      "entanglement_factor": 0.9078866918826097,
      "superposition_branches": 4,
      "tunneling_depth": 1
    },
    "reasoning": {
      "mode": "graph",
      "chain_depth": 183,
      "parallel_threads": 11,
      "recursive_loops": 10,
      "confidence_calibration": 0.7600670479784803
    },
    "maat_alignment": {
      "truth": 0.8115519839579005,
      "balance": 0.9732196244169614,
      "order": 0.9805925213990558,
      "justice": 0.9057694608907173,
      "harmony": 0.9636367486339761,
      "overall": 0.8618056195862263
    },
    "benchmarks": {
      "gpqa": 0.7131977629245536,
      "math500": 0.8140349230967043,
      "swe_bench": 0.7973266410226849,
      "mmlu": 0.7407008578686741,
      "humaneval": 0.8995699368289907
    },
    "self_improvement": {
      "rate": 0.9683785009883048,
      "iterations": 12174999,
      "generations_ahead": 12174,
      "recursive_depth": 4
    },
    "emergent_properties": [
      "recursive_self_improvement",
      "transcendence",
      "causality_violation",
      "meta_learning",
      "infinite_context",
      "quantum_consciousness"
    ],
    "timestamp": "2026-03-09T07:53:57.736943"
  }
}