{
  "iteration": 12144000,
  "elapsed_seconds": 51.09855890274048,
  "rate_per_second": 42153.83068042802,
  "latest_capability": {
    "id": 12143999,
    "name": "Quantum_Capability_12143999",
    "type": "agentic",
    "quantum_properties": {
      "state": "entangled",
      "coherence_level": 0.5394285780727388,
      "entanglement_factor": 0.09167213913016636,
      "superposition_branches": 6,
      "tunneling_depth": 0
    },
    "reasoning": {
      "mode": "tree",
      "chain_depth": 181,
      "parallel_threads": 6,
      "recursive_loops": 4,
      "confidence_calibration": 0.8339109956197123
    },
    "maat_alignment": {
      "truth": 0.8456559224687239,
      "balance": 0.8310838680513009,
      "order": 0.8788934862980472,
      "justice": 0.8068725837638351,
      "harmony": 0.8351783233073212,
      "overall": 0.9257100677328306
    },
    "benchmarks": {
      "gpqa": 0.8272279994547158,
      "math500": 0.7375526335553015,
      "swe_bench": 0.781249762403342,
      "mmlu": 0.7888805954500886,
      "humaneval": 0.8909431451240394
    },
    "self_improvement": {
      "rate": 0.9623020921785385,
      "iterations": 12143999,
      "generations_ahead": 12143,
      "recursive_depth": 5
    },
    "emergent_properties": [
      "meta_learning",
      "recursive_self_improvement",
      "transcendence",
      "omniscience"
    ],
    "timestamp": "2026-03-09T07:53:57.011707"
  }
}