{
  "iteration": 12693000,
  "elapsed_seconds": 63.642680644989014,
  "rate_per_second": 42471.49825567292,
  "latest_capability": {
    "id": 12692999,
    "name": "Quantum_Capability_12692999",
    "type": "reasoning",
    "quantum_properties": {
      "state": "superposition",
      "coherence_level": 0.780693583080756,
      "entanglement_factor": 0.9723768075570276,
      "superposition_branches": 9,
      "tunneling_depth": 0
    },
    "reasoning": {
      "mode": "tree",
      "chain_depth": 133,
      "parallel_threads": 13,
      "recursive_loops": 5,
      "confidence_calibration": 0.9039079436627016
    },
    "maat_alignment": {
      "truth": 0.8961808231288847,
      "balance": 0.9585239992141716,
      "order": 0.8642693048090827,
      "justice": 0.8145433960470202,
      "harmony": 0.8027291642375027,
      "overall": 0.8766489183753454
    },
    "benchmarks": {
      "gpqa": 0.7943299702093296,
      "math500": 0.6774380241786514,
      "swe_bench": 0.6701869122027175,
      "mmlu": 0.6667493308555412,
      "humaneval": 0.8026508690707521
    },
    "self_improvement": {
      "rate": 0.9840107978080177,
      "iterations": 12692999,
      "generations_ahead": 12692,
      "recursive_depth": 0
    },
    "emergent_properties": [
      "quantum_consciousness",
      "meta_learning",
      "transcendence",
      "self_modification",
      "omniscience"
    ],
    "timestamp": "2026-03-09T07:54:09.555829"
  }
}