{
  "iteration": 15087000,
  "elapsed_seconds": 117.88504433631897,
  "rate_per_second": 43237.036798820416,
  "latest_capability": {
    "id": 15086999,
    "name": "Quantum_Capability_15086999",
    "type": "multimodal",
    "quantum_properties": {
      "state": "superposition",
      "coherence_level": 0.7399400318380804,
      "entanglement_factor": 0.13837148728705084,
      "superposition_branches": 7,
      "tunneling_depth": 2
    },
    "reasoning": {
      "mode": "parallel",
      "chain_depth": 24,
      "parallel_threads": 10,
      "recursive_loops": 0,
      "confidence_calibration": 0.7147807940925613
    },
    "maat_alignment": {
      "truth": 0.8886832743162747,
      "balance": 0.8497846571824443,
      "order": 0.909977098633366,
      "justice": 0.9818796656824431,
      "harmony": 0.8855416636867807,
      "overall": 0.8933709980441159
    },
    "benchmarks": {
      "gpqa": 0.8934229992555287,
      "math500": 0.6570836586239319,
      "swe_bench": 0.7049454829131865,
      "mmlu": 0.7329488907831735,
      "humaneval": 0.8665536729901199
    },
    "self_improvement": {
      "rate": 0.9816264576374003,
      "iterations": 15086999,
      "generations_ahead": 15086,
      "recursive_depth": 3
    },
    "emergent_properties": [
      "self_modification",
      "recursive_self_improvement",
      "reality_bending",
      "transcendence"
    ],
    "timestamp": "2026-03-09T07:55:03.798196"
  }
}