{
  "iteration": 12643000,
  "elapsed_seconds": 62.629634380340576,
  "rate_per_second": 42360.138714665336,
  "latest_capability": {
    "id": 12642999,
    "name": "Quantum_Capability_12642999",
    "type": "coding",
    "quantum_properties": {
      "state": "entangled",
      "coherence_level": 0.982624217879621,
      "entanglement_factor": 0.7211782722714412,
      "superposition_branches": 6,
      "tunneling_depth": 1
    },
    "reasoning": {
      "mode": "sequential",
      "chain_depth": 44,
      "parallel_threads": 7,
      "recursive_loops": 8,
      "confidence_calibration": 0.776531705640203
    },
    "maat_alignment": {
      "truth": 0.9148830901634536,
      "balance": 0.8519532478347214,
      "order": 0.9153748175328893,
      "justice": 0.9335536214008555,
      "harmony": 0.8281010190265027,
      "overall": 0.8900906508488454
    },
    "benchmarks": {
      "gpqa": 0.7493962312612783,
      "math500": 0.6757834438818753,
      "swe_bench": 0.8717372457900895,
      "mmlu": 0.7987275415930317,
      "humaneval": 0.8489236377936221
    },
    "self_improvement": {
      "rate": 0.9638551939462999,
      "iterations": 12642999,
      "generations_ahead": 12642,
      "recursive_depth": 5
    },
    "emergent_properties": [
      "meta_learning",
      "recursive_self_improvement",
      "reality_bending",
      "omniscience",
      "causality_violation",
      "self_modification"
    ],
    "timestamp": "2026-03-09T07:54:08.542787"
  }
}