{
  "iteration": 11674000,
  "elapsed_seconds": 40.78864550590515,
  "rate_per_second": 41285.99954995318,
  "latest_capability": {
    "id": 11673999,
    "name": "Quantum_Capability_11673999",
    "type": "agentic",
    "quantum_properties": {
      "state": "coherent",
      "coherence_level": 0.6314784175728156,
      "entanglement_factor": 0.8344771023334638,
      "superposition_branches": 1,
      "tunneling_depth": 5
    },
    "reasoning": {
      "mode": "sequential",
      "chain_depth": 93,
      "parallel_threads": 1,
      "recursive_loops": 0,
      "confidence_calibration": 0.7142338999168408
    },
    "maat_alignment": {
      "truth": 0.9940001052651735,
      "balance": 0.8412854457612753,
      "order": 0.9731986769653349,
      "justice": 0.8263522802758302,
      "harmony": 0.8598707904152909,
      "overall": 0.9425595420782819
    },
    "benchmarks": {
      "gpqa": 0.9246885682488213,
      "math500": 0.8489716400069541,
      "swe_bench": 0.7413607548809995,
      "mmlu": 0.8675890578651035,
      "humaneval": 0.8167115783675095
    },
    "self_improvement": {
      "rate": 0.9711811461229849,
      "iterations": 11673999,
      "generations_ahead": 11673,
      "recursive_depth": 4
    },
    "emergent_properties": [
      "meta_learning",
      "causality_violation",
      "self_modification",
      "omniscience"
    ],
    "timestamp": "2026-03-09T07:53:46.701798"
  }
}