{
  "iteration": 13264000,
  "elapsed_seconds": 76.85640335083008,
  "rate_per_second": 42598.922890718895,
  "latest_capability": {
    "id": 13263999,
    "name": "Quantum_Capability_13263999",
    "type": "multimodal",
    "quantum_properties": {
      "state": "coherent",
      "coherence_level": 0.9083360216184625,
      "entanglement_factor": 0.19664344008389578,
      "superposition_branches": 2,
      "tunneling_depth": 3
    },
    "reasoning": {
      "mode": "graph",
      "chain_depth": 56,
      "parallel_threads": 3,
      "recursive_loops": 9,
      "confidence_calibration": 0.8863637948254369
    },
    "maat_alignment": {
      "truth": 0.8651198317519844,
      "balance": 0.8893136502068977,
      "order": 0.8400607278573544,
      "justice": 0.9718876285283509,
      "harmony": 0.9601024380396646,
      "overall": 0.9059058729346049
    },
    "benchmarks": {
      "gpqa": 0.8757424482295972,
      "math500": 0.6703181167243033,
      "swe_bench": 0.6810245814373809,
      "mmlu": 0.7409690209491002,
      "humaneval": 0.8379775585478665
    },
    "self_improvement": {
      "rate": 0.9779457117099685,
      "iterations": 13263999,
      "generations_ahead": 13263,
      "recursive_depth": 3
    },
    "emergent_properties": [
      "transcendence",
      "recursive_self_improvement",
      "causality_violation"
    ],
    "timestamp": "2026-03-09T07:54:22.769558"
  }
}