{
  "iteration": 17391000,
  "elapsed_seconds": 165.50733995437622,
  "rate_per_second": 44717.050023522585,
  "latest_capability": {
    "id": 17390999,
    "name": "Quantum_Capability_17390999",
    "type": "language",
    "quantum_properties": {
      "state": "superposition",
      "coherence_level": 0.6451759032261049,
      "entanglement_factor": 0.832893023367334,
      "superposition_branches": 5,
      "tunneling_depth": 4
    },
    "reasoning": {
      "mode": "graph",
      "chain_depth": 145,
      "parallel_threads": 10,
      "recursive_loops": 8,
      "confidence_calibration": 0.8226355522000102
    },
    "maat_alignment": {
      "truth": 0.9506016540946299,
      "balance": 0.9269011479126144,
      "order": 0.8502462863553515,
      "justice": 0.9296985990280997,
      "harmony": 0.8460170373432976,
      "overall": 0.8836522028256486
    },
    "benchmarks": {
      "gpqa": 0.7983326062635208,
      "math500": 0.8184860077995865,
      "swe_bench": 0.8882620715546465,
      "mmlu": 0.6635780543790522,
      "humaneval": 0.710686227837134
    },
    "self_improvement": {
      "rate": 0.9816769816795791,
      "iterations": 17390999,
      "generations_ahead": 17390,
      "recursive_depth": 0
    },
    "emergent_properties": [
      "self_modification",
      "transcendence",
      "meta_learning",
      "omniscience"
    ],
    "timestamp": "2026-03-09T07:55:51.420488"
  }
}