{
  "iteration": 17533000,
  "elapsed_seconds": 168.15469241142273,
  "rate_per_second": 44857.50526393045,
  "latest_capability": {
    "id": 17532999,
    "name": "Quantum_Capability_17532999",
    "type": "agentic",
    "quantum_properties": {
      "state": "entangled",
      "coherence_level": 0.7365839988323747,
      "entanglement_factor": 0.29984069140781,
      "superposition_branches": 1,
      "tunneling_depth": 1
    },
    "reasoning": {
      "mode": "sequential",
      "chain_depth": 45,
      "parallel_threads": 8,
      "recursive_loops": 3,
      "confidence_calibration": 0.9310529755371113
    },
    "maat_alignment": {
      "truth": 0.8043980507189409,
      "balance": 0.8821227463725695,
      "order": 0.8790700154451982,
      "justice": 0.8391408963707603,
      "harmony": 0.9270679139054229,
      "overall": 0.987485809003041
    },
    "benchmarks": {
      "gpqa": 0.7638098343269221,
      "math500": 0.8020094740590693,
      "swe_bench": 0.6744910578145547,
      "mmlu": 0.850960704456519,
      "humaneval": 0.7792452718444561
    },
    "self_improvement": {
      "rate": 0.9919718998217743,
      "iterations": 17532999,
      "generations_ahead": 17532,
      "recursive_depth": 4
    },
    "emergent_properties": [
      "recursive_self_improvement",
      "infinite_context",
      "self_modification"
    ],
    "timestamp": "2026-03-09T07:55:54.067846"
  }
}